imagedupes/__init__.py
imagedupes-1.2.9.dist-info/DESCRIPTION.rst
imagedupes-1.2.9.dist-info/METADATA
imagedupes-1.2.9.dist-info/RECORD
imagedupes-1.2.9.dist-info/WHEEL
imagedupes-1.2.9.dist-info/entry_points.txt
imagedupes-1.2.9.dist-info/metadata.json
imagedupes-1.2.9.dist-info/top_level.txt
