Metadata-Version: 2.0
Name: imagedupes
Version: 1.2.9
Summary: Python 3 CLI application for finding visually similar images
Home-page: https://github.com/ghemsley/imagedupes
Author: Graham Hemsley
Author-email: ghemsley@protonmail.ch
License: GPL3+
Keywords: image search deduplication
Platform: UNKNOWN
Classifier: Development Status :: 3 - Alpha
Classifier: Intended Audience :: End Users/Desktop
Classifier: Topic :: Multimedia :: Graphics
Classifier: License :: OSI Approved :: GNU General Public License v3 or later (GPLv3+)
Classifier: Programming Language :: Python :: 3.6
Requires-Dist: ImageHash
Requires-Dist: Pillow
Requires-Dist: rawpy
Requires-Dist: imageio
